pyhaste/__init__.py
pyhaste/analyzer.py
pyhaste/async_analyzer.py
pyhaste/common.py
pyhaste/test_analyzer.py
pyhaste-1.1.4.dist-info/METADATA
pyhaste-1.1.4.dist-info/WHEEL
pyhaste-1.1.4.dist-info/licenses/LICENSE.md
pyhaste-1.1.4.dist-info/RECORD
