Metadata-Version: 2.4
Name: PyHaste
Version: 1.1.4
Summary: Python code speed analyzer
License: BSD-3-Clause
License-File: LICENSE.md
Keywords: performance,measuring,benchmark,benchmarking,analyzer
Author: Janne Enberg
Author-email: janne.enberg@lietu.net
Requires-Python: >=3.11,<4.0
Classifier: License :: OSI Approved :: BSD License
Classifier: Programming Language :: Python :: 3
Classifier: Programming Language :: Python :: 3.11
Classifier: Programming Language :: Python :: 3.12
Classifier: Programming Language :: Python :: 3.13
Classifier: Programming Language :: Python :: 3.14
Requires-Dist: rich (>=13.7.1,<14.0.0)
Project-URL: Documentation, https://github.com/cocreators-ee/pyhaste/
Project-URL: Homepage, https://github.com/cocreators-ee/pyhaste/
Project-URL: Repository, https://github.com/cocreators-ee/pyhaste/
